API.rst
LICENSE.txt
MANIFEST.in
README.md
pyproject.toml
setup.py
stdeb.cfg
examples/simple.py
src/ads_wrap_system.h
src/c_lib.pxd
src/c_numarray.pxd
src/c_numpy.pxd
src/c_python.pxd
src/color_convert.c
src/color_convert.h
src/imops.c
src/imops.pyx
src/motmot.imops.egg-info/PKG-INFO
src/motmot.imops.egg-info/SOURCES.txt
src/motmot.imops.egg-info/dependency_links.txt
src/motmot.imops.egg-info/top_level.txt