Metadata-Version: 2.1
Name: motmot.imops
Version: 0.5.13
Summary: image format conversion (e.g. between MONO8, YUV422, and RGB)
Author-email: Andrew Straw <strawman@astraw.com>
Maintainer-email: Andrew Straw <strawman@astraw.com>
License: Copyright (c) 2004-2009, California Institute of Technology. All
Project-URL: homepage, http://code.astraw.com/projects/motmot/imops.html
Requires-Python: >=3.7
License-File: LICENSE.txt
